password_cracker/__init__.py
password_cracker/main.py
password_cracker/sock.py
password_cracker_DO_NOT_USE-0.0.1.dist-info/LICENSE
password_cracker_DO_NOT_USE-0.0.1.dist-info/METADATA
password_cracker_DO_NOT_USE-0.0.1.dist-info/WHEEL
password_cracker_DO_NOT_USE-0.0.1.dist-info/top_level.txt
password_cracker_DO_NOT_USE-0.0.1.dist-info/RECORD
