Metadata-Version: 2.1
Name: password-cracker-DO-NOT-USE
Version: 0.0.1
Summary: this package is for testing purposes
Author-email: ploni <almoni@gmail.com>
Classifier: Programming Language :: Python :: 3
Classifier: License :: OSI Approved :: MIT License
Classifier: Operating System :: Microsoft :: Windows
Requires-Python: >=3.7
License-File: LICENSE
